{
    "name": "fe_03_03657",
    "context_channel": 0,
    "context_text": "well nobody does it's amazing that y- look look eve all right i worked for delta airlines for many many years okay if you got an a) you got back fifty percent of your money a b) twenty five percent a c) ah ten percent okay and then they cut that out completely all right",
    "context_start": 419.64,
    "context_end": 438.55,
    "feedback": [
        {
            "name": "fe_03_03657",
            "channel": 1,
            "start": 438.83,
            "end": 439.43,
            "token": "okay"
        },
        {
            "name": "fe_03_02035",
            "channel": 1,
            "start": 536.81,
            "end": 537.73,
            "token": "wow"
        },
        {
            "name": "fe_03_05734",
            "channel": 1,
            "start": 214.71,
            "end": 215.3,
            "token": "mm"
        }
    ]
}