{
    "name": "fe_03_01919",
    "context_channel": 0,
    "context_text": "my husband he works fulltime he's a welder so he works out in the sun and and he works so hard and me i've been a you know stay at home mom probably for about ten years",
    "context_start": 486.39,
    "context_end": 494.38,
    "feedback": [
        {
            "name": "fe_03_01919",
            "channel": 1,
            "start": 494.44,
            "end": 494.89,
            "token": "uh-huh"
        },
        {
            "name": "fe_03_02302",
            "channel": 1,
            "start": 356.08,
            "end": 356.7,
            "token": "mm"
        },
        {
            "name": "fe_03_04354",
            "channel": 0,
            "start": 116.75,
            "end": 117.25,
            "token": "yeah"
        }
    ]
}