{
    "name": "fe_03_03031",
    "context_channel": 1,
    "context_text": "so so so why not i just call in and um you know right now i'm watching my two daughters so i really don't have anybody to carry on a conversation with",
    "context_start": 585.4,
    "context_end": 595.9,
    "feedback": [
        {
            "name": "fe_03_03031",
            "channel": 0,
            "start": 596.63,
            "end": 597.19,
            "token": "yeah"
        },
        {
            "name": "fe_03_03587",
            "channel": 1,
            "start": 254.7,
            "end": 255.42,
            "token": "sure"
        },
        {
            "name": "fe_03_04938",
            "channel": 0,
            "start": 588.29,
            "end": 588.78,
            "token": "uh-huh"
        }
    ]
}