{
    "name": "fe_03_05630",
    "context_channel": 1,
    "context_text": "pe-  perhaps perhaps you know i mean but then again kobe bryant wouldn't be anything without without shaquille o'neal you know you put the two of them together and it's like they're unstoppable",
    "context_start": 383.13,
    "context_end": 392.64,
    "feedback": [
        {
            "name": "fe_03_05630",
            "channel": 0,
            "start": 393.01,
            "end": 393.91,
            "token": "absolutely"
        },
        {
            "name": "fe_03_04678",
            "channel": 0,
            "start": 160.99,
            "end": 161.73,
            "token": "sure"
        },
        {
            "name": "fe_03_00835",
            "channel": 1,
            "start": 140.67,
            "end": 141.13,
            "token": "okay"
        }
    ]
}