{
    "name": "fe_03_05262",
    "context_channel": 0,
    "context_text": "no i haven't seen it i've heard about it though but i haven't seen it that's where the guy who was tryna find a woman",
    "context_start": 43.88,
    "context_end": 49.02,
    "feedback": [
        {
            "name": "fe_03_05262",
            "channel": 1,
            "start": 49.07,
            "end": 49.7,
            "token": "yes"
        },
        {
            "name": "fe_03_03511",
            "channel": 0,
            "start": 546.04,
            "end": 546.48,
            "token": "yeah"
        },
        {
            "name": "fe_03_01164",
            "channel": 1,
            "start": 209.93,
            "end": 210.62,
            "token": "oh"
        }
    ]
}