{
    "name": "fe_03_01854",
    "context_channel": 1,
    "context_text": "oh no maybe if you had to go to a library and sit for hours and look it up on a book and go back and forth just ah the speed of the computer being able to find all that thing makes it",
    "context_start": 200.05,
    "context_end": 209.09,
    "feedback": [
        {
            "name": "fe_03_01854",
            "channel": 0,
            "start": 209.3,
            "end": 209.85,
            "token": "yep"
        },
        {
            "name": "fe_03_02072",
            "channel": 1,
            "start": 99.45,
            "end": 100.28,
            "token": "right"
        },
        {
            "name": "fe_03_01857",
            "channel": 0,
            "start": 139.23,
            "end": 140.0,
            "token": "yeah"
        }
    ]
}